{
  "name" : "活动和运动",
  "style" : 1,
  "cover" : "football.png",
  "emoticons" : [
    {
      "img" : "26BD",
      "desc" : "[足球]"
    },
    {
      "img" : "1F6B4",
      "desc" : "[自行车]"
    },
    {
      "img" : "1F94B",
      "desc" : "[武术]"
    },
    {
      "img" : "26F8",
      "desc" : "[滑冰]"
    },
    {
      "img" : "1F381",
      "desc" : "[礼物]"
    },
    {
      "desc" : "[生日蛋糕]",
      "img" : "1F382"
    },
    {
      "img" : "1F383",
      "desc" : "[南瓜灯]"
    },
    {
      "img" : "1F384",
      "desc" : "[圣诞树]"
    },
    {
      "desc" : "[圣诞老人]",
      "img" : "1F385"
    },
    {
      "img" : "1F386",
      "desc" : "[焰火]"
    },
    {
      "img" : "1F387",
      "desc" : "[烟花]"
    },
    {
      "img" : "1F388",
      "desc" : "[气球]"
    },
    {
      "desc" : "[拉炮彩带]",
      "img" : "1F389"
    },
    {
      "desc" : "[五彩纸屑球]",
      "img" : "1F38A"
    },
    {
      "desc" : "[七夕树]",
      "img" : "1F38B"
    },
    {
      "desc" : "[交叉旗]",
      "img" : "1F38C"
    },
    {
      "img" : "1F38D",
      "desc" : "[门松]"
    },
    {
      "img" : "1F38E",
      "desc" : "[日本人形]"
    },
    {
      "desc" : "[鲤鱼旗]",
      "img" : "1F38F"
    },
    {
      "desc" : "[风铃]",
      "img" : "1F390"
    },
    {
      "img" : "1F391",
      "desc" : "[赏月]"
    },
    {
      "img" : "1F392",
      "desc" : "[书包]"
    },
    {
      "desc" : "[毕业帽]",
      "img" : "1F393"
    },
    {
      "img" : "1F396",
      "desc" : "[军功章]"
    },
    {
      "desc" : "[提示丝带]",
      "img" : "1F397"
    },
    {
      "img" : "1F399",
      "desc" : "[录音室麦克风]"
    },
    {
      "desc" : "[电平滑块]",
      "img" : "1F39A"
    },
    {
      "desc" : "[控制旋钮]",
      "img" : "1F39B"
    },
    {
      "desc" : "[影片帧]",
      "img" : "1F39E"
    },
    {
      "img" : "1F39F",
      "desc" : "[入场券]"
    },
    {
      "img" : "1F3A0",
      "desc" : "[旋转木马]"
    },
    {
      "desc" : "[摩天轮]",
      "img" : "1F3A1"
    },
    {
      "img" : "1F3A2",
      "desc" : "[过山车]"
    },
    {
      "desc" : "[钓鱼竿]",
      "img" : "1F3A3"
    },
    {
      "desc" : "[麦克风]",
      "img" : "1F3A4"
    },
    {
      "desc" : "[电影摄影机]",
      "img" : "1F3A5"
    },
    {
      "desc" : "[电影院]",
      "img" : "1F3A6"
    },
    {
      "img" : "1F3A7",
      "desc" : "[耳机]"
    },
    {
      "desc" : "[调色盘]",
      "img" : "1F3A8"
    },
    {
      "desc" : "[礼帽]",
      "img" : "1F3A9"
    },
    {
      "desc" : "[马戏团帐篷]",
      "img" : "1F3AA"
    },
    {
      "img" : "1F3AB",
      "desc" : "[票]"
    },
    {
      "img" : "1F3AC",
      "desc" : "[场记板]"
    },
    {
      "desc" : "[表演艺术]",
      "img" : "1F3AD"
    },
    {
      "desc" : "[游戏手柄]",
      "img" : "1F3AE"
    },
    {
      "img" : "1F3AF",
      "desc" : "[飞镖]"
    },
    {
      "desc" : "[老虎机]",
      "img" : "1F3B0"
    },
    {
      "desc" : "[台球]",
      "img" : "1F3B1"
    },
    {
      "desc" : "[骰子]",
      "img" : "1F3B2"
    },
    {
      "img" : "1F3B3",
      "desc" : "[保龄球]"
    },
    {
      "img" : "1F3B4",
      "desc" : "[花札]"
    },
    {
      "img" : "1F3B5",
      "desc" : "[音符]"
    },
    {
      "desc" : "[多个音符]",
      "img" : "1F3B6"
    },
    {
      "desc" : "[萨克斯管]",
      "img" : "1F3B7"
    },
    {
      "desc" : "[吉他]",
      "img" : "1F3B8"
    },
    {
      "img" : "1F3B9",
      "desc" : "[音乐键盘]"
    },
    {
      "img" : "1F3BA",
      "desc" : "[小号]"
    },
    {
      "desc" : "[小提琴]",
      "img" : "1F3BB"
    },
    {
      "desc" : "[乐谱]",
      "img" : "1F3BC"
    },
    {
      "desc" : "[运动背心]",
      "img" : "1F3BD"
    },
    {
      "desc" : "[网球]",
      "img" : "1F3BE"
    },
    {
      "desc" : "[滑雪]",
      "img" : "1F3BF"
    },
    {
      "desc" : "[篮球]",
      "img" : "1F3C0"
    },
    {
      "desc" : "[黑白方格旗]",
      "img" : "1F3C1"
    },
    {
      "desc" : "[滑雪板]",
      "img" : "1F3C2"
    },
    {
      "desc" : "[跑步者]",
      "img" : "1F3C3"
    },
    {
      "img" : "1F3C4",
      "desc" : "[冲浪]"
    },
    {
      "img" : "1F3C5",
      "desc" : "[奖牌]"
    },
    {
      "img" : "1F3C6",
      "desc" : "[奖杯]"
    },
    {
      "img" : "1F3C7",
      "desc" : "[赛马]"
    },
    {
      "img" : "1F3C8",
      "desc" : "[美式橄榄球]"
    },
    {
      "img" : "1F3C9",
      "desc" : "[英式橄榄球]"
    },
    {
      "img" : "1F3CA",
      "desc" : "[游泳]"
    },
    {
      "desc" : "[举重]",
      "img" : "1F3CB"
    },
    {
      "img" : "1F3CC",
      "desc" : "[打高尔夫的人]"
    },
    {
      "img" : "1F3CD",
      "desc" : "[摩托车]"
    },
    {
      "img" : "1F3CE",
      "desc" : "[赛车]"
    },
    {
      "img" : "1F3CF",
      "desc" : "[板球]"
    },
    {
      "img" : "1F3D0",
      "desc" : "[排球]"
    },
    {
      "desc" : "[曲棍球]",
      "img" : "1F3D1"
    },
    {
      "desc" : "[冰球]",
      "img" : "1F3D2"
    },
    {
      "desc" : "[乒乓球]",
      "img" : "1F3D3"
    },
    {
      "img" : "1F3D4",
      "desc" : "[雪山]"
    },
    {
      "img" : "1F3D5",
      "desc" : "[露营]"
    },
    {
      "desc" : "[沙滩伞]",
      "img" : "1F3D6"
    },
    {
      "desc" : "[施工]",
      "img" : "1F3D7"
    },
    {
      "img" : "1F3D8",
      "desc" : "[房屋建筑]"
    },
    {
      "img" : "1F3D9",
      "desc" : "[城市风光]"
    },
    {
      "desc" : "[废墟]",
      "img" : "1F3DA"
    },
    {
      "img" : "1F3DB",
      "desc" : "[古典建筑]"
    },
    {
      "img" : "1F3DC",
      "desc" : "[沙漠]"
    },
    {
      "desc" : "[无人荒岛]",
      "img" : "1F3DD"
    },
    {
      "desc" : "[国家公园]",
      "img" : "1F3DE"
    },
    {
      "img" : "1F3DF",
      "desc" : "[体育馆]"
    },
    {
      "desc" : "[房子]",
      "img" : "1F3E0"
    },
    {
      "img" : "1F3E1",
      "desc" : "[别墅]"
    },
    {
      "img" : "1F3E2",
      "desc" : "[办公楼]"
    },
    {
      "desc" : "[日本邮局]",
      "img" : "1F3E3"
    },
    {
      "img" : "1F3E4",
      "desc" : "[邮局]"
    },
    {
      "desc" : "[医院]",
      "img" : "1F3E5"
    },
    {
      "img" : "1F3E6",
      "desc" : "[银行]"
    },
    {
      "img" : "1F3E7",
      "desc" : "[取款机]"
    },
    {
      "desc" : "[酒店]",
      "img" : "1F3E8"
    },
    {
      "img" : "1F3E9",
      "desc" : "[情人酒店]"
    },
    {
      "img" : "1F3EA",
      "desc" : "[便利店]"
    },
    {
      "desc" : "[学校]",
      "img" : "1F3EB"
    },
    {
      "img" : "1F3EC",
      "desc" : "[商场]"
    },
    {
      "img" : "1F3ED",
      "desc" : "[工厂]"
    },
    {
      "img" : "1F3EE",
      "desc" : "[红灯笼]"
    },
    {
      "img" : "1F3EF",
      "desc" : "[日本城堡]"
    },
    {
      "img" : "1F3F0",
      "desc" : "[欧洲城堡]"
    },
    {
      "img" : "1F3F3",
      "desc" : "[白旗]"
    },
    {
      "img" : "1F3F4",
      "desc" : "[黑旗]"
    },
    {
      "desc" : "[圆形花饰]",
      "img" : "1F3F5"
    },
    {
      "img" : "1F3F7",
      "desc" : "[标签]"
    },
    {
      "img" : "1F3F8",
      "desc" : "[羽毛球]"
    },
    {
      "desc" : "[弓和箭]",
      "img" : "1F3F9"
    },
    {
      "img" : "1F3FA",
      "desc" : "[双耳瓶]"
    },
    {
      "img" : "1F3C0",
      "desc" : "[篮球]"
    },
    {
      "img" : "1F3C1",
      "desc" : "[黑白方格旗]"
    },
    {
      "img" : "1F3C2",
      "desc" : "[滑雪板]"
    },
    {
      "img" : "1F3C3",
      "desc" : "[跑步者]"
    },
    {
      "img" : "1F3C4",
      "desc" : "[冲浪]"
    },
    {
      "desc" : "[奖牌]",
      "img" : "1F3C5"
    },
    {
      "img" : "1F3C6",
      "desc" : "[奖杯]"
    },
    {
      "img" : "1F3C7",
      "desc" : "[赛马]"
    },
    {
      "desc" : "[美式橄榄球]",
      "img" : "1F3C8"
    },
    {
      "desc" : "[英式橄榄球]",
      "img" : "1F3C9"
    },
    {
      "desc" : "[游泳]",
      "img" : "1F3CA"
    },
    {
      "img" : "1F3CB",
      "desc" : "[举重]"
    },
    {
      "desc" : "[打高尔夫的人]",
      "img" : "1F3CC"
    },
    {
      "desc" : "[摩托车]",
      "img" : "1F3CD"
    },
    {
      "desc" : "[赛车]",
      "img" : "1F3CE"
    },
    {
      "desc" : "[板球]",
      "img" : "1F3CF"
    },
    {
      "desc" : "[蝴蝶结]",
      "img" : "1F380"
    }
  ]
}
